aitronos/__init__.py
aitronos/authentication.py
aitronos/config.py
aitronos/helper.py
aitronos/AppHive/__init__.py
aitronos/AppHive/user_management.py
aitronos/StreamLine/__init__.py
aitronos/StreamLine/module.py
aitronos/api_keys/__init__.py
aitronos/assistant_messaging/__init__.py
aitronos/assistant_messaging/module.py
aitronos/assistants/__init__.py
aitronos/audio/__init__.py
aitronos/chat_messaging/__init__.py
aitronos/cli/__init__.py
aitronos/cli/cli.py
aitronos/cli/main.py
aitronos/cli/utils.py
aitronos/cli/commands/__init__.py
aitronos/cli/commands/feature_x.py
aitronos/cli/commands/init_project.py
aitronos/cli/commands/hello_world_project/config.freddy.json
aitronos/cli/commands/hello_world_project/requirements.txt
aitronos/cli/commands/hello_world_project/resources/__init__.py
aitronos/cli/commands/hello_world_project/resources/current_org.py
aitronos/cli/commands/hello_world_project/resources/current_user.py
aitronos/cli/commands/hello_world_project/resources/helpers.py
aitronos/cli/commands/hello_world_project/resources/org_data.json
aitronos/cli/commands/hello_world_project/resources/parameter.py
aitronos/cli/commands/hello_world_project/resources/parameters.json
aitronos/cli/commands/hello_world_project/resources/user_data.json
aitronos/cli/commands/hello_world_project/src/main/hello_world.py
aitronos/cli/commands/hello_world_with_parameters/config.freddy.json
aitronos/cli/commands/hello_world_with_parameters/requirements.txt
aitronos/cli/commands/hello_world_with_parameters/resources/__init__.py
aitronos/cli/commands/hello_world_with_parameters/resources/current_user.py
aitronos/cli/commands/hello_world_with_parameters/resources/helpers.py
aitronos/cli/commands/hello_world_with_parameters/resources/org_data.json
aitronos/cli/commands/hello_world_with_parameters/resources/parameter.py
aitronos/cli/commands/hello_world_with_parameters/resources/parameters.json
aitronos/cli/commands/hello_world_with_parameters/resources/user_data.json
aitronos-4.5.7.dist-info/METADATA
aitronos-4.5.7.dist-info/WHEEL
aitronos-4.5.7.dist-info/entry_points.txt
aitronos-4.5.7.dist-info/top_level.txt
aitronos-4.5.7.dist-info/RECORD
