Metadata-Version: 2.1
Name: aitronos
Version: 4.5.7
Summary: A Python package for interacting with the Freddy API and other Aitronos services
Home-page: https://github.com/Freddy-Development/aitronos-python-package
Author: Phillip Loacker
Author-email: phillip.loacker@aitronos.com
Project-URL: Bug Tracker, https://github.com/Freddy-Development/aitronos-python-package/issues
Project-URL: Documentation, https://github.com/Freddy-Development/aitronos-python-package#readme
Project-URL: Source Code, https://github.com/Freddy-Development/aitronos-python-package
Keywords: aitronos,freddy,api,machine learning,ai
Classifier: Development Status :: 3 - Alpha
Classifier: Intended Audience :: Developers
Classifier: Topic :: Software Development :: Libraries :: Python Modules
Classifier: Programming Language :: Python :: 3
Classifier: Programming Language :: Python :: 3.7
Classifier: Programming Language :: Python :: 3.8
Classifier: Programming Language :: Python :: 3.9
Classifier: Programming Language :: Python :: 3.10
Classifier: Programming Language :: Python :: 3.11
Classifier: Programming Language :: Python :: 3.12
Classifier: License :: OSI Approved :: MIT License
Classifier: Operating System :: OS Independent
Requires-Python: >=3.7
Requires-Dist: click >=8.0.0
Requires-Dist: requests >=2.25.0
Requires-Dist: typing-extensions >=4.0.0
Requires-Dist: setuptools >=68.2.0
Requires-Dist: tqdm >=4.66.5
Requires-Dist: urllib3 >=2.2.2
Requires-Dist: certifi >=2024.7.4
Requires-Dist: idna >=3.7
Requires-Dist: optional >=0.0.1
Requires-Dist: httpx >=0.27.2
Requires-Dist: regex >=2024.5.15
Requires-Dist: pytest >=8.3.3
Requires-Dist: aitronos-logger >=0.1.6
Requires-Dist: setuptools ~=68.2.0
Requires-Dist: requests ~=2.32.3
Requires-Dist: tqdm ~=4.66.5
Requires-Dist: pip ~=23.2.1
Requires-Dist: wheel ~=0.41.2
Requires-Dist: urllib3 ~=2.2.2
Requires-Dist: certifi ~=2024.7.4
Requires-Dist: idna ~=3.7
Requires-Dist: optional ~=0.0.1
Requires-Dist: httpx ~=0.27.2
Requires-Dist: regex ~=2024.5.15
Requires-Dist: pytest ==8.3.3
Requires-Dist: aitronos-logger ~=0.1.6
Provides-Extra: dev
Requires-Dist: pytest >=6.0.0 ; extra == 'dev'
Requires-Dist: pytest-cov >=2.0.0 ; extra == 'dev'
Requires-Dist: black >=21.0.0 ; extra == 'dev'
Requires-Dist: mypy >=0.900 ; extra == 'dev'
